ledger_language_server/__init__.py
ledger_language_server-0.1.0.dist-info/METADATA
ledger_language_server-0.1.0.dist-info/WHEEL
ledger_language_server-0.1.0.dist-info/RECORD
